wagtail_switch_block/__init__.py
wagtail_switch_block/apps.py
wagtail_switch_block/block_registry.py
wagtail_switch_block/blocks.py
wagtail_switch_block/function_specifier.py
wagtail_switch_block/static/wagtail_switch_block/css/wagtail_switch_block.css
wagtail_switch_block/static/wagtail_switch_block/js/wagtail_switch_block.js
wagtail_switch_block/templates/wagtail_switch_block/switch_block.html
wagtail_switch_block-4.1.0.dist-info/AUTHORS.txt
wagtail_switch_block-4.1.0.dist-info/LICENSE.txt
wagtail_switch_block-4.1.0.dist-info/METADATA
wagtail_switch_block-4.1.0.dist-info/WHEEL
wagtail_switch_block-4.1.0.dist-info/top_level.txt
wagtail_switch_block-4.1.0.dist-info/zip-safe
wagtail_switch_block-4.1.0.dist-info/RECORD
